[
  {
    "userUid": "285443892",
    "taskType": "daily",
    "totalParsed": 106,
    "submitted": 106,
    "failed": 0,
    "whitelistSkipped": 0,
    "durationSeconds": 1018,
    "timestamp": "2026-06-20T23:35:53.157722",
    "clientType": "android-apk",
    "received_at": "2026-06-20T15:36:15.733729"
  },
  {
    "userUid": "285443892",
    "taskType": "daily",
    "totalParsed": 106,
    "submitted": 106,
    "failed": 0,
    "whitelistSkipped": 0,
    "durationSeconds": 0,
    "timestamp": "2026-06-20T23:40:49.314105",
    "clientType": "android-apk",
    "received_at": "2026-06-20T15:40:50.417623"
  },
  {
    "userUid": "285443892",
    "taskType": "daily",
    "totalParsed": 106,
    "submitted": 106,
    "failed": 0,
    "whitelistSkipped": 0,
    "durationSeconds": 0,
    "timestamp": "2026-06-20T23:40:56.350189",
    "clientType": "android-apk",
    "received_at": "2026-06-20T15:40:56.720309"
  },
  {
    "userUid": "287781096",
    "taskType": "daily",
    "timestamp": "2026-06-20T15:52:42.772Z",
    "clientType": "chrome-extension",
    "totalParsed": 102,
    "submitted": 102,
    "failed": 0,
    "whitelistSkipped": 0,
    "durationSeconds": 829,
    "received_at": "2026-06-20T15:52:44.162411"
  },
  {
    "userUid": "279597787",
    "taskType": "temp",
    "timestamp": "2026-06-20T15:53:36.219Z",
    "clientType": "chrome-extension",
    "totalParsed": 2415,
    "submitted": 2042,
    "failed": 348,
    "whitelistSkipped": 25,
    "durationSeconds": 35406,
    "received_at": "2026-06-20T15:53:37.494796"
  },
  {
    "userUid": "234448879",
    "taskType": "temp",
    "timestamp": "2026-06-20T15:54:13.334Z",
    "clientType": "chrome-extension",
    "totalParsed": 646,
    "submitted": 626,
    "failed": 0,
    "whitelistSkipped": 20,
    "durationSeconds": 16780,
    "received_at": "2026-06-20T15:54:14.042749"
  },
  {
    "userUid": "279597787",
    "taskType": "local",
    "timestamp": "2026-06-20T16:05:45.172Z",
    "clientType": "chrome-extension",
    "totalParsed": 10,
    "submitted": 10,
    "failed": 0,
    "whitelistSkipped": 0,
    "durationSeconds": 45,
    "received_at": "2026-06-20T16:05:46.235069"
  },
  {
    "userUid": "231425470",
    "taskType": "daily",
    "timestamp": "2026-06-20T16:06:31.692Z",
    "clientType": "chrome-extension",
    "totalParsed": 968,
    "submitted": 0,
    "failed": 968,
    "whitelistSkipped": 0,
    "durationSeconds": 7700,
    "received_at": "2026-06-20T16:06:31.914253"
  },
  {
    "userUid": "279597787",
    "taskType": "local",
    "timestamp": "2026-06-20T16:11:02.892Z",
    "clientType": "chrome-extension",
    "totalParsed": 42,
    "submitted": 42,
    "failed": 0,
    "whitelistSkipped": 0,
    "durationSeconds": 207,
    "received_at": "2026-06-20T16:11:04.308141"
  },
  {
    "userUid": "218411376",
    "taskType": "temp",
    "totalParsed": 662,
    "submitted": 631,
    "failed": 10,
    "whitelistSkipped": 20,
    "durationSeconds": 7730,
    "timestamp": "2026-06-21T00:13:33.307632",
    "clientType": "android-apk",
    "received_at": "2026-06-20T16:13:33.453756"
  }
]