[
  {
    "userUid": "177237175",
    "taskType": "temp",
    "totalParsed": 833,
    "submitted": 830,
    "failed": 2,
    "whitelistSkipped": 0,
    "durationSeconds": 14377,
    "timestamp": "2026-06-23T17:38:38.909118",
    "clientType": "android-apk",
    "received_at": "2026-06-23T09:39:00.333441"
  },
  {
    "userUid": "291032081",
    "taskType": "temp",
    "totalParsed": 1304,
    "submitted": 1,
    "failed": 1,
    "whitelistSkipped": 0,
    "durationSeconds": 14,
    "timestamp": "2026-06-23T17:38:44.317463",
    "clientType": "android-apk",
    "received_at": "2026-06-23T09:39:20.405200"
  },
  {
    "userUid": "174189238",
    "taskType": "temp",
    "timestamp": "2026-06-23T09:45:37.345Z",
    "clientType": "chrome-extension",
    "totalParsed": 1097,
    "submitted": 1097,
    "failed": 0,
    "whitelistSkipped": 0,
    "durationSeconds": 11409,
    "received_at": "2026-06-23T09:45:21.051459"
  }
]