[
  {
    "userUid": "285491139",
    "taskType": "temp",
    "totalParsed": 348,
    "submitted": 346,
    "failed": 2,
    "whitelistSkipped": 0,
    "durationSeconds": 5370,
    "timestamp": "2026-06-27T13:04:40.969252",
    "clientType": "android-apk",
    "received_at": "2026-06-27T05:05:04.364223"
  },
  {
    "userUid": "156407051",
    "taskType": "temp",
    "totalParsed": 399,
    "submitted": 396,
    "failed": 3,
    "whitelistSkipped": 0,
    "durationSeconds": 6104,
    "timestamp": "2026-06-27T13:16:53.896193",
    "clientType": "android-apk",
    "received_at": "2026-06-27T05:16:56.244094"
  },
  {
    "userUid": "279597787",
    "taskType": "local",
    "timestamp": "2026-06-27T05:19:15.864Z",
    "clientType": "chrome-extension",
    "totalParsed": 65,
    "submitted": 65,
    "failed": 0,
    "whitelistSkipped": 0,
    "durationSeconds": 323,
    "received_at": "2026-06-27T05:19:16.924559"
  },
  {
    "userUid": "56721642",
    "taskType": "local",
    "timestamp": "2026-06-27T05:22:04.425Z",
    "clientType": "chrome-extension",
    "totalParsed": 892,
    "submitted": 891,
    "failed": 1,
    "whitelistSkipped": 0,
    "durationSeconds": 6133,
    "received_at": "2026-06-27T05:22:05.163828"
  },
  {
    "userUid": "63282608",
    "taskType": "temp",
    "timestamp": "2026-06-27T05:27:14.509Z",
    "clientType": "chrome-extension",
    "totalParsed": 2940,
    "submitted": 2126,
    "failed": 818,
    "whitelistSkipped": 0,
    "durationSeconds": 0,
    "received_at": "2026-06-27T05:27:15.169411"
  },
  {
    "userUid": "227537513",
    "taskType": "temp",
    "totalParsed": 1096,
    "submitted": 1094,
    "failed": 2,
    "whitelistSkipped": 0,
    "durationSeconds": 13186,
    "timestamp": "2026-06-27T13:29:26.245205",
    "clientType": "android-apk",
    "received_at": "2026-06-27T05:29:26.638780"
  },
  {
    "userUid": "275836660",
    "taskType": "local",
    "timestamp": "2026-06-27T05:41:22.117Z",
    "clientType": "chrome-extension",
    "totalParsed": 61,
    "submitted": 61,
    "failed": 0,
    "whitelistSkipped": 0,
    "durationSeconds": 331,
    "received_at": "2026-06-27T05:41:24.486930"
  },
  {
    "userUid": "285314153",
    "taskType": "local",
    "timestamp": "2026-06-27T05:44:08.974Z",
    "clientType": "chrome-extension",
    "totalParsed": 72,
    "submitted": 72,
    "failed": 0,
    "whitelistSkipped": 0,
    "durationSeconds": 424,
    "received_at": "2026-06-27T05:44:10.378614"
  },
  {
    "userUid": "275161773",
    "taskType": "daily",
    "totalParsed": 1454,
    "submitted": 1185,
    "failed": 152,
    "whitelistSkipped": 117,
    "durationSeconds": 15515,
    "timestamp": "2026-06-27T13:44:50.124035",
    "clientType": "android-apk",
    "received_at": "2026-06-27T05:44:51.634646"
  }
]